gamble/__init__.py
gamble/errors.py
gamble/models/__init__.py
gamble/models/cards.py
gamble/models/dice.py
gamble/models/golf.py
gamble-0.14.0.dist-info/LICENSE
gamble-0.14.0.dist-info/METADATA
gamble-0.14.0.dist-info/WHEEL
gamble-0.14.0.dist-info/RECORD
