Metadata-Version: 2.1
Name: gamble
Version: 0.14.0
Summary: a collection of gambling classes/tools
Home-page: https://github.com/jpetrucciani/gamble
Author: jacobi petrucciani
Author-email: j@cobi.dev
Requires-Python: >=3.10
Classifier: License :: OSI Approved :: MIT License
Classifier: Programming Language :: Python :: 3
Classifier: Programming Language :: Python :: 3.10
Classifier: Programming Language :: Python :: 3.11
Classifier: Programming Language :: Python :: 3.12
Classifier: Programming Language :: Python :: 3.13
Classifier: Programming Language :: Python :: Implementation :: CPython
Classifier: Programming Language :: Python :: Implementation :: PyPy
Project-URL: Repository, https://github.com/jpetrucciani/gamble
